{"data":{"_id":1000,"properties":{"fullName":{"name":"fullName","kind":"scalar","getter":false,"setter":false,"type":"string","array":false,"runtimeType":"string"},"accountID":{"name":"accountID","kind":"scalar","getter":false,"setter":false,"type":"string","array":false,"runtimeType":"string"},"email":{"name":"email","kind":"scalar","getter":false,"setter":false,"type":"string","array":false,"runtimeType":"string"},"transactions":{"name":"transactions","kind":"1:m","cascade":["persist"],"mappedBy":"account","type":"Transaction","array":false,"runtimeType":"Collection<Transaction, object>"},"token":{"name":"token","kind":"scalar","persist":false,"getter":false,"setter":false,"type":"string","array":false,"runtimeType":"string","optional":true}},"primaryKeys":[],"filters":{},"hooks":{},"indexes":[],"uniques":[],"className":"Account","path":"./src/modules/account/account.entity.ts","name":"Account","abstract":false,"internal":true,"constructorParams":["fullName","email","password","accountID"],"toJsonParams":[],"extends":"BaseEntity","useCache":true,"collection":"account"},"origin":"./src/modules/account/account.entity.ts","hash":"c14b8b1cc00b8da3c00cc35b9a7232a8","version":"6.4.2"}
